{"ongoing_trials": {"tuner0": "03"}, "hyperparameters": {"space": [{"class_name": "Int", "config": {"name": "kernel_size", "default": null, "conditions": [], "min_value": 2, "max_value": 4, "step": 1, "sampling": "linear"}}, {"class_name": "Int", "config": {"name": "filters", "default": null, "conditions": [], "min_value": 32, "max_value": 128, "step": 32, "sampling": "linear"}}, {"class_name": "Int", "config": {"name": "pool_size", "default": null, "conditions": [], "min_value": 2, "max_value": 3, "step": 1, "sampling": "linear"}}, {"class_name": "Int", "config": {"name": "lstm_units", "default": null, "conditions": [], "min_value": 32, "max_value": 128, "step": 32, "sampling": "linear"}}, {"class_name": "Float", "config": {"name": "dropout", "default": 0.1, "conditions": [], "min_value": 0.1, "max_value": 0.5, "step": 0.1, "sampling": "linear"}}], "values": {"kernel_size": 2, "filters": 32, "pool_size": 2, "lstm_units": 32, "dropout": 0.1}}, "start_order": ["00", "01", "02", "03"], "end_order": ["00", "01", "02"], "run_times": {"00": 1, "01": 1, "02": 1}, "retry_queue": [], "seed": 6348, "seed_state": 6368, "tried_so_far": ["5aa0af4bd332232d1165dae08d035209", "fa1bbe13239e7d1a1e2222efe6288eab", "56f31796ecb69a4e5af88581ec45860f", "88a3bc6a47fdcc9ba94cb77a212be940"], "id_to_hash": {"00": "56f31796ecb69a4e5af88581ec45860f", "01": "fa1bbe13239e7d1a1e2222efe6288eab", "02": "88a3bc6a47fdcc9ba94cb77a212be940", "03": "5aa0af4bd332232d1165dae08d035209"}, "display": {"search_start": "2025-01-24T18:11:33.611208", "trial_start": {"00": "2025-01-24T18:11:33.611208", "01": "2025-01-24T18:11:46.404209", "02": "2025-01-24T18:11:47.168210"}, "trial_number": {"00": 1, "01": 2, "02": 3}}}